odoo/addons/stock_move_quick_lot/README.rst
odoo/addons/stock_move_quick_lot/__init__.py
odoo/addons/stock_move_quick_lot/__manifest__.py
odoo/addons/stock_move_quick_lot/i18n/es.po
odoo/addons/stock_move_quick_lot/i18n/it.po
odoo/addons/stock_move_quick_lot/i18n/stock_move_quick_lot.pot
odoo/addons/stock_move_quick_lot/i18n/stock_pack_operation_quick_lot.pot
odoo/addons/stock_move_quick_lot/models/__init__.py
odoo/addons/stock_move_quick_lot/models/stock_move.py
odoo/addons/stock_move_quick_lot/readme/CONFIGURE.rst
odoo/addons/stock_move_quick_lot/readme/CONTRIBUTORS.rst
odoo/addons/stock_move_quick_lot/readme/DESCRIPTION.rst
odoo/addons/stock_move_quick_lot/readme/USAGE.rst
odoo/addons/stock_move_quick_lot/static/description/icon.png
odoo/addons/stock_move_quick_lot/static/description/icon.svg
odoo/addons/stock_move_quick_lot/static/description/index.html
odoo/addons/stock_move_quick_lot/tests/__init__.py
odoo/addons/stock_move_quick_lot/tests/test_stock_move_quick_lot.py
odoo/addons/stock_move_quick_lot/views/stock_view.xml
odoo14_addon_stock_move_quick_lot-14.0.1.0.1.dev8.dist-info/METADATA
odoo14_addon_stock_move_quick_lot-14.0.1.0.1.dev8.dist-info/WHEEL
odoo14_addon_stock_move_quick_lot-14.0.1.0.1.dev8.dist-info/top_level.txt
odoo14_addon_stock_move_quick_lot-14.0.1.0.1.dev8.dist-info/RECORD
